lib_azure/__init__.py
lib_azure/ai_document_intelligence.py
lib_azure-1.1.11.dist-info/METADATA
lib_azure-1.1.11.dist-info/WHEEL
lib_azure-1.1.11.dist-info/RECORD
