Metadata-Version: 2.3
Name: lib-azure
Version: 1.1.11
Summary: 
Author: Nathan Blum
Author-email: n.blum@student.tudelft.nl
Requires-Python: >=3.10
Classifier: Programming Language :: Python :: 3
Classifier: Programming Language :: Python :: 3.10
Classifier: Programming Language :: Python :: 3.11
Classifier: Programming Language :: Python :: 3.12
Classifier: Programming Language :: Python :: 3.13
Requires-Dist: azure-ai-formrecognizer (>=3.3.3,<4.0.0)
Requires-Dist: azure-core (>=1.35.0,<2.0.0)
Requires-Dist: babel (>=2.17.0,<3.0.0)
Requires-Dist: dateparser (>=1.2.2,<2.0.0)
Requires-Dist: lib-invoice (>=0.1.1,<0.2.0)
Requires-Dist: lib-utilys (>=0.1.3,<0.2.0)
